airavat/__init__.py
airavat/arm_template.py
airavat-0.0.32.dist-info/LICENSE
airavat-0.0.32.dist-info/METADATA
airavat-0.0.32.dist-info/WHEEL
airavat-0.0.32.dist-info/top_level.txt
airavat-0.0.32.dist-info/RECORD
