Metadata-Version: 2.1
Name: airavat
Version: 0.0.32
Summary: Audit Utilities for Azure Data Factory- To find the common engineering hacks and reduce manual interventions.
Home-page: https://github.com/Saumitra24/airavat
Author: Saumitra Rawat
Author-email: saumitra.rawat@gmail.com
Classifier: Programming Language :: Python :: 3
Classifier: License :: OSI Approved :: MIT License
Classifier: Operating System :: OS Independent
License-File: LICENSE
